gitcommitlogger/.logsignore
gitcommitlogger/__init__.py
gitcommitlogger/__main__.py
gitcommitlogger/example_commits.json
gitcommitlogger-1.2.5.dist-info/METADATA
gitcommitlogger-1.2.5.dist-info/WHEEL
gitcommitlogger-1.2.5.dist-info/entry_points.txt
gitcommitlogger-1.2.5.dist-info/licenses/LICENSE
gitcommitlogger-1.2.5.dist-info/RECORD
