Metadata-Version: 2.1
Name: gitcommitlogger
Version: 1.2.5
Summary: Logs statistics for specific commits in CSV form and optionally sends them as JSON to a web api.
Project-URL: Homepage, https://github.com/bloombar/gitcommitlogger
Project-URL: Repository, https://github.com/bloombar/gitcommitlogger.git
Project-URL: Bug Tracker, https://github.com/bloombar/gitcommitlogger/issues
Author-email: Foo Barstein <foo.barstein@onepotcooking.com>
License:                     GNU GENERAL PUBLIC LICENSE
License-File: LICENSE
Keywords: analysis,commits,developer,git,logging,report
Classifier: Intended Audience :: Education
Classifier: License :: OSI Approved :: GNU General Public License v3 (GPLv3)
Classifier: Operating System :: OS Independent
Classifier: Programming Language :: Python :: 3
Requires-Python: >=3.7
Provides-Extra: dev
Requires-Dist: pytest; extra == 'dev'
